Metadata-Version: 1.0
Name: kspifka
Version: 0.0.3
Summary: Distributed scraping framework for Python.
Home-page: https://github.com/kwx1996/kspifka
Author: kong
Author-email: tomngp@163.com
License: UNKNOWN
Platform: UNKNOWN
